LICENSE
MANIFEST.in
README.md
setup.py
carrousel/__init__.py
carrousel/admin.py
carrousel/models.py
carrousel/views.py
carrousel/locale/es/LC_MESSAGES/django.mo
carrousel/locale/es/LC_MESSAGES/django.po
carrousel/migrations/0001_initial.py
carrousel/migrations/__init__.py
carrousel/templates/carrousel/carrousel.html
carrousel/templates/carrousel/indicators.html
carrousel/templates/carrousel/slide.html
carrousel/templatetags/__init__.py
carrousel/templatetags/carousel_tags.py
django_carrousel.egg-info/PKG-INFO
django_carrousel.egg-info/SOURCES.txt
django_carrousel.egg-info/dependency_links.txt
django_carrousel.egg-info/not-zip-safe
django_carrousel.egg-info/requires.txt
django_carrousel.egg-info/top_level.txt