Metadata-Version: 1.1
Name: django-carrousel
Version: 2.1
Summary: A django application that allows adding carrousel with slides on your web site.
Home-page: https://github.com/devartis/django-carrousel
Author: Pablo García
Author-email: poli@devartis.com
License: Apache License
Platform: OS Independent
Classifier: Development Status :: 5 - Production/Stable
Classifier: Environment :: Web Environment
Classifier: Framework :: Django
Classifier: Intended Audience :: Developers
Classifier: License :: OSI Approved :: Apache Software License
Classifier: Operating System :: OS Independent
Classifier: Programming Language :: Python
Classifier: Topic :: Internet :: WWW/HTTP :: Dynamic Content
Classifier: Topic :: Software Development
Classifier: Programming Language :: Python :: 2.6
Classifier: Programming Language :: Python :: 2.7
